ak_docx/__init__.py
ak_docx/main.py
ak_docx/read.py
ak_docx/write.py
ak_docx-0.0.2.dist-info/LICENSE
ak_docx-0.0.2.dist-info/WHEEL
ak_docx-0.0.2.dist-info/METADATA
ak_docx-0.0.2.dist-info/RECORD
