Metadata-Version: 2.1
Name: ak_docx
Version: 0.0.2
Summary: Docx parsing library
Author-email: Arun Kishore <pypi@rpakishore.co.in>
Requires-Python: >=3.9
Classifier: License :: OSI Approved :: MIT License
Requires-Dist: pytest>=7.2.1
Requires-Dist: python-docx>=0.8.11
Requires-Dist: ak_file>=0.0.2
Requires-Dist: docx2txt>=0.8
Project-URL: Home, https://github.com/rpakishore/ak_docx
